<?xml version="1.0" encoding="UTF-8"?>
<issues format="6" by="lint 8.2.2" type="baseline" client="gradle" dependencies="false" name="AGP (8.2.2)" variant="all" version="8.2.2">

    <issue
        id="FragmentTagUsage"
        message="Replace the &lt;fragment> tag with FragmentContainerView."
        errorLine1="        &lt;fragment"
        errorLine2="         ~~~~~~~~">
        <location
            file="src/main/res/layout/activity_main.xml"
            line="52"
            column="10"/>
    </issue>

    <issue
        id="MissingInflatedId"
        message="`@layout/activity_custom_scanner` does not contain a declaration with id `zxing_viewfinder_view`"
        errorLine1="        viewfinderView = findViewById(R.id.zxing_viewfinder_view);"
        errorLine2="                                      ~~~~~~~~~~~~~~~~~~~~~~~~~~">
        <location
            file="src/main/java/example/zxing/CustomScannerActivity.java"
            line="40"
            column="39"/>
    </issue>

    <issue
        id="RedundantLabel"
        message="Redundant label can be removed"
        errorLine1="            android:label=&quot;@string/app_name&quot;"
        errorLine2="            ~~~~~~~~~~~~~~~~~~~~~~~~~~~~~~~~">
        <location
            file="src/main/AndroidManifest.xml"
            line="14"
            column="13"/>
    </issue>

    <issue
        id="GradleDependency"
        message="A newer version of com.google.code.gson:gson than 2.9.1 is available: 2.10.1"
        errorLine1="    implementation &apos;com.google.code.gson:gson:2.9.1&apos;"
        errorLine2="                   ~~~~~~~~~~~~~~~~~~~~~~~~~~~~~~~~~">
        <location
            file="build.gradle"
            line="83"
            column="20"/>
    </issue>

    <issue
        id="GradleDependency"
        message="A newer version of androidx.appcompat:appcompat than 1.3.1 is available: 1.7.0"
        errorLine1="    implementation &apos;androidx.appcompat:appcompat:1.3.1&apos;"
        errorLine2="                   ~~~~~~~~~~~~~~~~~~~~~~~~~~~~~~~~~~~~">
        <location
            file="build.gradle"
            line="84"
            column="20"/>
    </issue>

    <issue
        id="GradleDependency"
        message="A newer version of androidx.activity:activity than 1.3.1 is available: 1.9.3"
        errorLine1="    implementation &quot;androidx.activity:activity:1.3.1&quot;"
        errorLine2="                   ~~~~~~~~~~~~~~~~~~~~~~~~~~~~~~~~~~">
        <location
            file="build.gradle"
            line="86"
            column="20"/>
    </issue>

    <issue
        id="GradleDependency"
        message="A newer version of androidx.constraintlayout:constraintlayout than 2.1.4 is available: 2.2.0"
        errorLine1="    implementation &apos;androidx.constraintlayout:constraintlayout:2.1.4&apos;"
        errorLine2="                   ~~~~~~~~~~~~~~~~~~~~~~~~~~~~~~~~~~~~~~~~~~~~~~~~~~">
        <location
            file="build.gradle"
            line="88"
            column="20"/>
    </issue>

    <issue
        id="GradleDependency"
        message="A newer version of com.android.tools:desugar_jdk_libs than 1.1.5 is available: 2.1.3"
        errorLine1="    coreLibraryDesugaring &apos;com.android.tools:desugar_jdk_libs:1.1.5&apos;"
        errorLine2="                          ~~~~~~~~~~~~~~~~~~~~~~~~~~~~~~~~~~~~~~~~~~">
        <location
            file="build.gradle"
            line="91"
            column="27"/>
    </issue>

    <issue
        id="LockedOrientationActivity"
        message="Expecting `android:screenOrientation=&quot;unspecified&quot;` or `&quot;fullSensor&quot;` for this activity so the user can use the application in any orientation and provide a great experience on Chrome OS devices"
        errorLine1="            android:screenOrientation=&quot;portrait&quot;"
        errorLine2="            ~~~~~~~~~~~~~~~~~~~~~~~~~~~~~~~~~~~~">
        <location
            file="src/main/AndroidManifest.xml"
            line="33"
            column="13"/>
    </issue>

    <issue
        id="UsingOnClickInXml"
        message="Use databinding or explicit wiring of click listener in code"
        errorLine1="        android:onClick=&quot;switchFlashlight&quot;/>"
        errorLine2="        ~~~~~~~~~~~~~~~~~~~~~~~~~~~~~~~~~~">
        <location
            file="src/main/res/layout/activity_custom_scanner.xml"
            line="23"
            column="9"/>
    </issue>

    <issue
        id="UsingOnClickInXml"
        message="Use databinding or explicit wiring of click listener in code"
        errorLine1="            android:onClick=&quot;scanBarcode&quot;/>"
        errorLine2="            ~~~~~~~~~~~~~~~~~~~~~~~~~~~~~">
        <location
            file="src/main/res/layout/activity_main.xml"
            line="20"
            column="13"/>
    </issue>

    <issue
        id="UsingOnClickInXml"
        message="Use databinding or explicit wiring of click listener in code"
        errorLine1="            android:onClick=&quot;scanPDF417&quot;/>"
        errorLine2="            ~~~~~~~~~~~~~~~~~~~~~~~~~~~~">
        <location
            file="src/main/res/layout/activity_main.xml"
            line="26"
            column="13"/>
    </issue>

    <issue
        id="UsingOnClickInXml"
        message="Use databinding or explicit wiring of click listener in code"
        errorLine1="            android:onClick=&quot;scanBarcodeInverted&quot;/>"
        errorLine2="            ~~~~~~~~~~~~~~~~~~~~~~~~~~~~~~~~~~~~~">
        <location
            file="src/main/res/layout/activity_main.xml"
            line="32"
            column="13"/>
    </issue>

    <issue
        id="UsingOnClickInXml"
        message="Use databinding or explicit wiring of click listener in code"
        errorLine1="            android:onClick=&quot;scanMixedBarcodes&quot;/>"
        errorLine2="            ~~~~~~~~~~~~~~~~~~~~~~~~~~~~~~~~~~~">
        <location
            file="src/main/res/layout/activity_main.xml"
            line="38"
            column="13"/>
    </issue>

    <issue
        id="UsingOnClickInXml"
        message="Use databinding or explicit wiring of click listener in code"
        errorLine1="            android:onClick=&quot;scanBarcodeCustomLayout&quot;/>"
        errorLine2="            ~~~~~~~~~~~~~~~~~~~~~~~~~~~~~~~~~~~~~~~~~">
        <location
            file="src/main/res/layout/activity_main.xml"
            line="44"
            column="13"/>
    </issue>

    <issue
        id="UsingOnClickInXml"
        message="Use databinding or explicit wiring of click listener in code"
        errorLine1="            android:onClick=&quot;scanBarcodeFrontCamera&quot;/>"
        errorLine2="            ~~~~~~~~~~~~~~~~~~~~~~~~~~~~~~~~~~~~~~~~">
        <location
            file="src/main/res/layout/activity_main.xml"
            line="50"
            column="13"/>
    </issue>

    <issue
        id="UsingOnClickInXml"
        message="Use databinding or explicit wiring of click listener in code"
        errorLine1="            android:onClick=&quot;scanContinuous&quot;/>"
        errorLine2="            ~~~~~~~~~~~~~~~~~~~~~~~~~~~~~~~~">
        <location
            file="src/main/res/layout/activity_main.xml"
            line="64"
            column="13"/>
    </issue>

    <issue
        id="UsingOnClickInXml"
        message="Use databinding or explicit wiring of click listener in code"
        errorLine1="            android:onClick=&quot;scanToolbar&quot;/>"
        errorLine2="            ~~~~~~~~~~~~~~~~~~~~~~~~~~~~~">
        <location
            file="src/main/res/layout/activity_main.xml"
            line="70"
            column="13"/>
    </issue>

    <issue
        id="UsingOnClickInXml"
        message="Use databinding or explicit wiring of click listener in code"
        errorLine1="            android:onClick=&quot;scanCustomScanner&quot;/>"
        errorLine2="            ~~~~~~~~~~~~~~~~~~~~~~~~~~~~~~~~~~~">
        <location
            file="src/main/res/layout/activity_main.xml"
            line="76"
            column="13"/>
    </issue>

    <issue
        id="UsingOnClickInXml"
        message="Use databinding or explicit wiring of click listener in code"
        errorLine1="            android:onClick=&quot;scanMarginScanner&quot;/>"
        errorLine2="            ~~~~~~~~~~~~~~~~~~~~~~~~~~~~~~~~~~~">
        <location
            file="src/main/res/layout/activity_main.xml"
            line="82"
            column="13"/>
    </issue>

    <issue
        id="UsingOnClickInXml"
        message="Use databinding or explicit wiring of click listener in code"
        errorLine1="            android:onClick=&quot;scanWithTimeout&quot;/>"
        errorLine2="            ~~~~~~~~~~~~~~~~~~~~~~~~~~~~~~~~~">
        <location
            file="src/main/res/layout/activity_main.xml"
            line="88"
            column="13"/>
    </issue>

    <issue
        id="UsingOnClickInXml"
        message="Use databinding or explicit wiring of click listener in code"
        errorLine1="            android:onClick=&quot;tabs&quot;/>"
        errorLine2="            ~~~~~~~~~~~~~~~~~~~~~~">
        <location
            file="src/main/res/layout/activity_main.xml"
            line="94"
            column="13"/>
    </issue>

    <issue
        id="UsingOnClickInXml"
        message="Use databinding or explicit wiring of click listener in code"
        errorLine1="            android:onClick=&quot;about&quot;/>"
        errorLine2="            ~~~~~~~~~~~~~~~~~~~~~~~">
        <location
            file="src/main/res/layout/activity_main.xml"
            line="100"
            column="13"/>
    </issue>

    <issue
        id="UsingOnClickInXml"
        message="Use databinding or explicit wiring of click listener in code"
        errorLine1="            android:onClick=&quot;pause&quot; />"
        errorLine2="            ~~~~~~~~~~~~~~~~~~~~~~~">
        <location
            file="src/main/res/layout/continuous_scan.xml"
            line="27"
            column="13"/>
    </issue>

    <issue
        id="UsingOnClickInXml"
        message="Use databinding or explicit wiring of click listener in code"
        errorLine1="            android:onClick=&quot;resume&quot; />"
        errorLine2="            ~~~~~~~~~~~~~~~~~~~~~~~~">
        <location
            file="src/main/res/layout/continuous_scan.xml"
            line="33"
            column="13"/>
    </issue>

    <issue
        id="DataExtractionRules"
        message="The attribute `android:allowBackup` is deprecated from Android 12 and higher and may be removed in future versions. Consider adding the attribute `android:dataExtractionRules` specifying an `@xml` resource which configures cloud backups and device transfers on Android 12 and higher."
        errorLine1="        android:allowBackup=&quot;false&quot;"
        errorLine2="                             ~~~~~">
        <location
            file="src/main/AndroidManifest.xml"
            line="8"
            column="30"/>
    </issue>

    <issue
        id="UnusedResources"
        message="The resource `R.menu.menu_tabbed_scanning` appears to be unused"
        errorLine1="&lt;menu xmlns:android=&quot;http://schemas.android.com/apk/res/android&quot;"
        errorLine2="^">
        <location
            file="src/main/res/menu/menu_tabbed_scanning.xml"
            line="1"
            column="1"/>
    </issue>

    <issue
        id="UnusedResources"
        message="The resource `R.string.scan_barcode_with_request_code` appears to be unused"
        errorLine1="    &lt;string name=&quot;scan_barcode_with_request_code&quot;>Scan Barcode with customized request code&lt;/string>"
        errorLine2="            ~~~~~~~~~~~~~~~~~~~~~~~~~~~~~~~~~~~~~">
        <location
            file="src/main/res/values/strings.xml"
            line="6"
            column="13"/>
    </issue>

    <issue
        id="ContentDescription"
        message="Missing `contentDescription` attribute on image"
        errorLine1="    &lt;ImageView"
        errorLine2="     ~~~~~~~~~">
        <location
            file="src/main/res/layout/continuous_scan.xml"
            line="42"
            column="6"/>
    </issue>

    <issue
        id="HardcodedText"
        message="Hardcoded string &quot;Scan PDF417&quot;, should use `@string` resource"
        errorLine1="            android:text=&quot;Scan PDF417&quot;"
        errorLine2="            ~~~~~~~~~~~~~~~~~~~~~~~~~~">
        <location
            file="src/main/res/layout/activity_main.xml"
            line="25"
            column="13"/>
    </issue>

    <issue
        id="HardcodedText"
        message="Hardcoded string &quot;Scan Inverted&quot;, should use `@string` resource"
        errorLine1="            android:text=&quot;Scan Inverted&quot;"
        errorLine2="            ~~~~~~~~~~~~~~~~~~~~~~~~~~~~">
        <location
            file="src/main/res/layout/activity_main.xml"
            line="31"
            column="13"/>
    </issue>

    <issue
        id="HardcodedText"
        message="Hardcoded string &quot;Scan Normal and Inverted&quot;, should use `@string` resource"
        errorLine1="            android:text=&quot;Scan Normal and Inverted&quot;"
        errorLine2="            ~~~~~~~~~~~~~~~~~~~~~~~~~~~~~~~~~~~~~~~">
        <location
            file="src/main/res/layout/activity_main.xml"
            line="37"
            column="13"/>
    </issue>

    <issue
        id="HardcodedText"
        message="Hardcoded string &quot;Pause&quot;, should use `@string` resource"
        errorLine1="            android:text=&quot;Pause&quot;"
        errorLine2="            ~~~~~~~~~~~~~~~~~~~~">
        <location
            file="src/main/res/layout/continuous_scan.xml"
            line="26"
            column="13"/>
    </issue>

    <issue
        id="HardcodedText"
        message="Hardcoded string &quot;Resume&quot;, should use `@string` resource"
        errorLine1="            android:text=&quot;Resume&quot;"
        errorLine2="            ~~~~~~~~~~~~~~~~~~~~~">
        <location
            file="src/main/res/layout/continuous_scan.xml"
            line="32"
            column="13"/>
    </issue>

    <issue
        id="RtlHardcoded"
        message="Consider replacing `android:layout_alignParentLeft` with `android:layout_alignParentStart=&quot;true&quot;` to better support right-to-left layouts"
        errorLine1="        android:layout_alignParentLeft=&quot;true&quot;"
        errorLine2="        ~~~~~~~~~~~~~~~~~~~~~~~~~~~~~~">
        <location
            file="src/main/res/layout/capture_appcompat.xml"
            line="32"
            column="9"/>
    </issue>

    <issue
        id="RtlHardcoded"
        message="Consider replacing `android:layout_alignParentLeft` with `android:layout_alignParentStart=&quot;true&quot;` to better support right-to-left layouts"
        errorLine1="        android:layout_alignParentLeft=&quot;true&quot;"
        errorLine2="        ~~~~~~~~~~~~~~~~~~~~~~~~~~~~~~">
        <location
            file="src/main/res/layout/capture_small.xml"
            line="25"
            column="9"/>
    </issue>

    <issue
        id="RtlHardcoded"
        message="Consider replacing `android:layout_alignParentRight` with `android:layout_alignParentEnd=&quot;true&quot;` to better support right-to-left layouts"
        errorLine1="        android:layout_alignParentRight=&quot;true&quot;"
        errorLine2="        ~~~~~~~~~~~~~~~~~~~~~~~~~~~~~~~">
        <location
            file="src/main/res/layout/capture_small.xml"
            line="26"
            column="9"/>
    </issue>

    <issue
        id="RtlHardcoded"
        message="Consider replacing `android:layout_toLeftOf` with `android:layout_toStartOf=&quot;@+id/centerHorizont&quot;` to better support right-to-left layouts"
        errorLine1="        android:layout_toLeftOf=&quot;@+id/centerHorizont&quot;>"
        errorLine2="        ~~~~~~~~~~~~~~~~~~~~~~~">
        <location
            file="src/main/res/layout/continuous_scan.xml"
            line="21"
            column="9"/>
    </issue>

    <issue
        id="RtlHardcoded"
        message="Consider replacing `android:layout_toRightOf` with `android:layout_toEndOf=&quot;@id/centerHorizont&quot;` to better support right-to-left layouts"
        errorLine1="        android:layout_toRightOf=&quot;@id/centerHorizont&quot;"
        errorLine2="        ~~~~~~~~~~~~~~~~~~~~~~~~">
        <location
            file="src/main/res/layout/continuous_scan.xml"
            line="45"
            column="9"/>
    </issue>

    <issue
        id="RtlHardcoded"
        message="Consider replacing `android:layout_alignParentRight` with `android:layout_alignParentEnd=&quot;true&quot;` to better support right-to-left layouts"
        errorLine1="        android:layout_alignParentRight=&quot;true&quot;"
        errorLine2="        ~~~~~~~~~~~~~~~~~~~~~~~~~~~~~~~">
        <location
            file="src/main/res/layout/continuous_scan.xml"
            line="47"
            column="9"/>
    </issue>

</issues>
